setup.cfg
setup.py
bgcore/__init__.py
bgcore/labelfilter.py
bgcore/logging.py
bgcore/re.py
bgcore/request.py
bgcore/tsv.py
bgcore.egg-info/PKG-INFO
bgcore.egg-info/SOURCES.txt
bgcore.egg-info/dependency_links.txt
bgcore.egg-info/top_level.txt
bgcore/obo/__init__.py
bgcore/obo/parser.py
bgcore/obo/stream.py
bgcore/obo/tree.py